LICENSE.txt
MANIFEST.in
README.rst
TODO
pavement.py
requirements.txt
setup.py
docs/.gitignore
docs/conf.py
docs/index.rst
docs/readme.rst
docs/usage.rst
sphinxcontrib/__init__.py
sphinxcontrib/eagle.py
sphinxcontrib_eagle.egg-info/PKG-INFO
sphinxcontrib_eagle.egg-info/SOURCES.txt
sphinxcontrib_eagle.egg-info/dependency_links.txt
sphinxcontrib_eagle.egg-info/namespace_packages.txt
sphinxcontrib_eagle.egg-info/not-zip-safe
sphinxcontrib_eagle.egg-info/requires.txt
sphinxcontrib_eagle.egg-info/top_level.txt