Metadata-Version: 1.1
Name: sphinxcontrib-eagle
Version: 0.0.9
Summary: Sphinx extension to include image or partlist of eagle schematic or board
Home-page: https://github.com/ponty/sphinxcontrib-eagle
Author: ponty
Author-email: UNKNOWN
License: BSD
Keywords: sphinx eagle
Platform: UNKNOWN
Classifier: License :: OSI Approved :: BSD License
Classifier: Natural Language :: English
Classifier: Operating System :: POSIX :: Linux
Classifier: Programming Language :: Python
Classifier: Environment :: Console
Classifier: Environment :: Web Environment
Classifier: Intended Audience :: Developers
Classifier: Topic :: Documentation
Classifier: Topic :: Utilities
